academic_claim_analyzer/__init__.py
academic_claim_analyzer/_version.py
academic_claim_analyzer/batch_processor.py
academic_claim_analyzer/main.py
academic_claim_analyzer/models.py
academic_claim_analyzer/paper_ranker.py
academic_claim_analyzer/paper_scraper.py
academic_claim_analyzer/query_formulator.py
academic_claim_analyzer/test_scraper.py
academic_claim_analyzer/search/__init__.py
academic_claim_analyzer/search/base.py
academic_claim_analyzer/search/bibtex.py
academic_claim_analyzer/search/core_search.py
academic_claim_analyzer/search/openalex_search.py
academic_claim_analyzer/search/scopus_search.py
academic_claim_analyzer-1.0.1.dist-info/LICENSE
academic_claim_analyzer-1.0.1.dist-info/METADATA
academic_claim_analyzer-1.0.1.dist-info/WHEEL
academic_claim_analyzer-1.0.1.dist-info/top_level.txt
academic_claim_analyzer-1.0.1.dist-info/RECORD
